pAsynCrawler/__init__.py
pAsynCrawler/file_cache.py
pAsynCrawler/parallels.py
pAsynCrawler/pyasyncrawler.py
pAsynCrawler/urls_constructor.py
pAsynCrawler/utils.py
pasyncrawler-0.1.11.dist-info/LICENSE
pasyncrawler-0.1.11.dist-info/WHEEL
pasyncrawler-0.1.11.dist-info/METADATA
pasyncrawler-0.1.11.dist-info/RECORD
