Metadata-Version: 2.1
Name: pAsynCrawler
Version: 0.1.11
Summary: 
Author-email: Michael Hsieh <m9810223@gmail.com>
Requires-Python: >=3.6,<4
Classifier: Environment :: Web Environment
Classifier: Framework :: aiohttp
Classifier: Framework :: AsyncIO
Classifier: Programming Language :: Python :: 3
Classifier: Programming Language :: Python
Classifier: Topic :: Internet :: WWW/HTTP
Classifier: Topic :: Internet
Classifier: Topic :: Software Development :: Libraries :: Python Modules
Classifier: Topic :: Software Development :: Libraries
Classifier: Topic :: Software Development
Requires-Dist: aiohttp >=3.8.1
Requires-Dist: beautifulsoup4 >=4.10.0 ; extra == "demo"
Project-URL: Bug Tracker, https://github.com/m9810223/pAsynCrawler/issues
Project-URL: Source, https://github.com/m9810223/pAsynCrawler
Project-URL: documentation, https://github.com/m9810223/pAsynCrawler#readme
Project-URL: homepage, https://github.com/m9810223/pAsynCrawler
Provides-Extra: demo
